webhook_guardian/__init__.py
webhook_guardian/cli.py
webhook_guardian/exceptions.py
webhook_guardian/guardian.py
webhook_guardian/validator.py
webhook_guardian-0.1.1.dist-info/licenses/LICENSE
webhook_guardian-0.1.1.dist-info/METADATA
webhook_guardian-0.1.1.dist-info/WHEEL
webhook_guardian-0.1.1.dist-info/entry_points.txt
webhook_guardian-0.1.1.dist-info/top_level.txt
webhook_guardian-0.1.1.dist-info/RECORD
