Metadata-Version: 2.4
Name: webhook-guardian
Version: 0.1.1
Summary: A security-focused Python library for validating and handling webhooks safely
Home-page: https://github.com/rebzie22/webhook-guardian
Author: Jordan Guck
Author-email: Jordan Guck <your.email@example.com>
Maintainer-email: Jordan Guck <your.email@example.com>
License: MIT
Project-URL: Homepage, https://github.com/rebzie22/webhook-guardian
Project-URL: Documentation, https://github.com/rebzie22/webhook-guardian#readme
Project-URL: Repository, https://github.com/rebzie22/webhook-guardian.git
Project-URL: Bug Tracker, https://github.com/rebzie22/webhook-guardian/issues
Project-URL: Changelog, https://github.com/rebzie22/webhook-guardian/releases
Keywords: webhook,security,validation,hmac,cryptography
Classifier: Development Status :: 3 - Alpha
Classifier: Intended Audience :: Developers
Classifier: License :: OSI Approved :: MIT License
Classifier: Operating System :: OS Independent
Classifier: Programming Language :: Python :: 3
Classifier: Programming Language :: Python :: 3.8
Classifier: Programming Language :: Python :: 3.9
Classifier: Programming Language :: Python :: 3.10
Classifier: Programming Language :: Python :: 3.11
Classifier: Programming Language :: Python :: 3.12
Classifier: Topic :: Security
Classifier: Topic :: Internet :: WWW/HTTP
Classifier: Topic :: Software Development :: Libraries :: Python Modules
Requires-Python: >=3.8
License-File: LICENSE
Requires-Dist: cryptography>=3.4.8
Requires-Dist: requests>=2.25.1
Requires-Dist: python-dateutil>=2.8.2
Provides-Extra: dev
Requires-Dist: pytest>=7.0.0; extra == "dev"
Requires-Dist: pytest-cov>=4.0.0; extra == "dev"
Requires-Dist: black>=23.0.0; extra == "dev"
Requires-Dist: flake8>=6.0.0; extra == "dev"
Requires-Dist: mypy>=1.0.0; extra == "dev"
Requires-Dist: pre-commit>=3.0.0; extra == "dev"
Provides-Extra: examples
Requires-Dist: flask>=2.0.0; extra == "examples"
Dynamic: author
Dynamic: home-page
Dynamic: license-file
Dynamic: requires-python
